ipsh/__init__.py
ipsh/__main__.py
ipsh/history.py
ipsh/i18n.py
ipsh/interpreters.py
ipsh/main.py
ipsh/parsers.py
ipsh/py.typed
ipsh/locale/de/LC_MESSAGES/argparse.mo
ipsh/locale/de/LC_MESSAGES/ipsh.mo
ipsh-0.4.1.dist-info/METADATA
ipsh-0.4.1.dist-info/WHEEL
ipsh-0.4.1.dist-info/entry_points.txt
ipsh-0.4.1.dist-info/top_level.txt
ipsh-0.4.1.dist-info/RECORD
