Metadata-Version: 2.1
Name: ipsh
Version: 0.4.1
Summary: interactive pseudo shell
Author-email: Rainer Schwarzbach <undisclosed@example.com>
License: MIT License
Project-URL: Homepage, https://gitlab.com/blackstream-x/pseudoshell
Project-URL: Documentation, https://blackstream-x.gitlab.io/pseudoshell
Project-URL: CI, https://gitlab.com/blackstream-x/pseudoshell/-/pipelines
Project-URL: Bug Tracker, https://gitlab.com/blackstream-x/pseudoshell/-/issues
Project-URL: Repository, https://gitlab.com/blackstream-x/pseudoshell.git
Keywords: readline,shell
Classifier: Development Status :: 4 - Beta
Classifier: Environment :: Console
Classifier: Intended Audience :: Developers
Classifier: Intended Audience :: System Administrators
Classifier: License :: OSI Approved :: MIT License
Classifier: Operating System :: OS Independent
Classifier: Programming Language :: Python :: 3
Classifier: Programming Language :: Python :: 3.11
Classifier: Programming Language :: Python :: 3.12
Classifier: Programming Language :: Python :: 3.13
Classifier: Programming Language :: Python :: 3 :: Only
Classifier: Topic :: Software Development :: Libraries
Classifier: Topic :: Utilities
Requires-Python: >=3.11
